{"IcoMoonType":"selection","icons":[{"icon":{"paths":["M562.735 876.451v138.24h-526.429v-138.24h191.302v-706.56c-7.447 11.171-20.015 23.738-37.702 37.702-16.756 13.033-35.84 26.065-57.251 39.098-21.411 12.102-43.753 22.342-67.025 30.72-22.342 8.378-42.822 12.567-61.44 12.567v-142.429c25.135 0 50.269-6.516 75.404-19.549 26.065-13.033 50.269-27.927 72.611-44.684 22.342-17.687 40.029-33.513 53.062-47.476 13.964-13.964 21.411-21.411 22.342-22.342h157.789v862.953h177.338z"],"attrs":[{"fill":"rgb(255, 255, 255)"}],"width":577,"isMulticolor":false,"isMulticolor2":false,"grid":0,"tags":["1"]},"attrs":[{"fill":"rgb(255, 255, 255)"}],"properties":{"order":3,"id":0,"name":"1","prevSize":32,"code":59648},"setIdx":0,"setId":0,"iconIdx":0}],"height":1024,"metadata":{"name":"icomoon"},"preferences":{"showGlyphs":true,"showCodes":true,"showQuickUse":true,"showQuickUse2":true,"showSVGs":true,"fontPref":{"prefix":"icon-","metadata":{"fontFamily":"icomoon"},"metrics":{"emSize":1024,"baseline":6.25,"whitespace":50},"embed":false},"imagePref":{"prefix":"icon-","png":true,"useClassSelector":true,"color":0,"bgColor":16777215},"historySize":50}}